hydra_utils/__init__.py
hydra_utils/__version__.py
hydra_utils/dummy.py
hydra_utils/py.typed
hydra_utils/utils.py
hydra_utils-0.3.2.dist-info/METADATA
hydra_utils-0.3.2.dist-info/WHEEL
hydra_utils-0.3.2.dist-info/entry_points.txt
hydra_utils-0.3.2.dist-info/licenses/LICENSE
hydra_utils-0.3.2.dist-info/RECORD
