Metadata-Version: 2.4
Name: hydra-utils
Version: 0.3.2
Summary: Utilities for hydra-core library
Project-URL: Repository, https://github.com/rcmdnk/hydra-utils
Project-URL: Homepage, https://github.com/rcmdnk/hydra-utils
Author-email: rcmdnk <rcmdnk@gmail.com>
License-Expression: Apache-2.0
License-File: LICENSE
Keywords: hydra,hydra-core,hydra-utils
Requires-Python: <3.14,>=3.10
Requires-Dist: hydra-core>=1.3.2
Requires-Dist: joblib>=1.4.2
